README.rst
limbs.py
setup.py
limbs.egg-info/PKG-INFO
limbs.egg-info/SOURCES.txt
limbs.egg-info/dependency_links.txt
limbs.egg-info/top_level.txt