Metadata-Version: 1.1
Name: limbs
Version: 0.4
Summary: like mime, but simpler - a simple, human-readable file format
